konlpy_homi/__init__.py
konlpy_homi/app.py
konlpy_homi/example.py
konlpy_homi/typed.py
konlpy_homi/api/__init__.py
konlpy_homi/api/v0alpha/__init__.py
konlpy_homi/api/v0alpha/global_pb2.py
konlpy_homi/api/v0alpha/global_pb2_grpc.py
konlpy_homi/api/v0alpha/hannanum_pb2.py
konlpy_homi/api/v0alpha/hannanum_pb2_grpc.py
konlpy_homi/api/v0alpha/kkma_pb2.py
konlpy_homi/api/v0alpha/kkma_pb2_grpc.py
konlpy_homi/api/v0alpha/komoran_pb2.py
konlpy_homi/api/v0alpha/komoran_pb2_grpc.py
konlpy_homi/api/v0alpha/mecab_pb2.py
konlpy_homi/api/v0alpha/mecab_pb2_grpc.py
konlpy_homi/api/v0alpha/okt_pb2.py
konlpy_homi/api/v0alpha/okt_pb2_grpc.py
konlpy_homi/clients/__init__.py
konlpy_homi/clients/base.py
konlpy_homi/clients/hannanum_client.py
konlpy_homi/clients/kkma_client.py
konlpy_homi/clients/komoran_client.py
konlpy_homi/clients/mecab_client.py
konlpy_homi/clients/okt_client.py
konlpy_homi/monkeypatch/__init__.py
konlpy_homi/services/__init__.py
konlpy_homi/services/hannanum.py
konlpy_homi/services/kkma.py
konlpy_homi/services/komoran.py
konlpy_homi/services/mecab.py
konlpy_homi/services/okt.py
konlpy_homi/services/utils.py
konlpy_homi-0.0.2.dist-info/LICENSE
konlpy_homi-0.0.2.dist-info/METADATA
konlpy_homi-0.0.2.dist-info/WHEEL
konlpy_homi-0.0.2.dist-info/top_level.txt
konlpy_homi-0.0.2.dist-info/RECORD
