Metadata-Version: 2.1
Name: konlpy-homi
Version: 0.0.2
Summary: remote konlpy client
Home-page: https://github.com/wesky93/KoNLPy-homi
Maintainer: wesky93
Maintainer-email: wesky93@gmail.com
License: GNU GPLv3
Platform: UNKNOWN
Classifier: Intended Audience :: Developers
Classifier: Operating System :: OS Independent
Classifier: Programming Language :: Python
Classifier: Programming Language :: Python :: 3
Classifier: Programming Language :: Python :: 3 :: Only
Classifier: Programming Language :: Python :: 3.8
Classifier: Topic :: Software Development :: Libraries :: Python Modules
Requires-Python: >=3.8
Requires-Dist: homi (>=0.1.8)
Requires-Dist: grpc-requests (>=0.0.7)
Requires-Dist: konlpy (==0.5.2)
